---
title: Jvm规范之字节码文件格式
date: 2018-07-24 18:50:20
tags:
- Jvm
---
在之前一片文章中介绍了Jvm规范中的第三章：Java源码是如何转换为Jvm指令。那么按照顺序这篇文章将会介绍Jvm规范的{% link 第四章 https://docs.oracle.com/javase/specs/jvms/se8/html/jvms-4.html %}class文件格式。既然是字节码文件那么我们仍然需要通过javap -v class文件名来查看相关信息，不过还有这里我可以推荐一个工具可以帮助方便解读class文件，这款工具名字叫做jclasslib，有兴趣的可以前往{% link github下载 https://github.com/ingokegel/jclasslib/releases %}。
<!-- more -->
# 字节码整体结构
{% codeblock 官网结构 %}
ClassFile {
    u4             magic;
    u2             minor_version;
    u2             major_version;
    u2             constant_pool_count;
    cp_info        constant_pool[constant_pool_count-1];
    u2             access_flags;
    u2             this_class;
    u2             super_class;
    u2             interfaces_count;
    u2             interfaces[interfaces_count];
    u2             fields_count;
    field_info     fields[fields_count];
    u2             methods_count;
    method_info    methods[methods_count];
    u2             attributes_count;
    attribute_info attributes[attributes_count];
}
{% endcodeblock %}
这是官网展示的字节码抽象结构。在官网的介绍中单个为itme(项)，一个或多个项组成Table(表)，最简单区分结构中是否存在[]，有即为Table。magic项提供了类的标识号。minor_version，major_version项表示这个字节码文件允许运行虚拟机的次要版本和主要版本。constant_pool_count项表示字节码常量池的数量。constant_pool[]表将常量池中的每个常量都展示出来。access_flags代表类或接口的访问修饰符；this_class项表示当前类；super_class项表示继承的类；interfaces_count项表示实现的接口数量；interfaces[]表展示所有实现的接口；fields_count项代表成员变量个数；fields[]表展示所有的成员变量；methods_count项表示方法数；methods[]表展示所有的方法；attributes_count项表示附加信息；attributes[]表展示所有的附加信息。
# Javap实例解读
官网的结构为我们描绘了具体的结构，但是我们只能通过javap进行反编译来了解其中的信息，下面我们通过一个简单的javap实例来的阐述字节码文件的各个部分。
{% codeblock 示例代码 %}
public class Test implements Cloneable {
	protected String name;

	public String getName() {
		name = "Hello World";
		return name;
	}
}
{% endcodeblock %}{% codeblock Javap -v %}
Classfile /E:/Workspaces/eclipse/vertx/target/classes/com/toss/vertx/Test.class
  Last modified 2018-7-30; size 508 bytes
  MD5 checksum 4ed1a33dd001f1c91b2a878e07d9a2d5
  Compiled from "Test.java"
public class com.toss.vertx.Test implements java.lang.Cloneable
  minor version: 0
  major version: 52
  flags: ACC_PUBLIC, ACC_SUPER
Constant pool:
   #1 = Class              #2             // com/toss/vertx/Test
   #2 = Utf8               com/toss/vertx/Test
   #3 = Class              #4             // java/lang/Object
   #4 = Utf8               java/lang/Object
   #5 = Class              #6             // java/lang/Cloneable
   #6 = Utf8               java/lang/Cloneable
   #7 = Utf8               name
   #8 = Utf8               Ljava/lang/String;
   #9 = Utf8               <init>
  #10 = Utf8               (Ljava/lang/String;)V
  #11 = Utf8               Code
  #12 = Methodref          #3.#13         // java/lang/Object."<init>":()V
  #13 = NameAndType        #9:#14         // "<init>":()V
  #14 = Utf8               ()V
  #15 = Fieldref           #1.#16         // com/toss/vertx/Test.name:Ljava/lang/String;
  #16 = NameAndType        #7:#8          // name:Ljava/lang/String;
  #17 = Utf8               LineNumberTable
  #18 = Utf8               LocalVariableTable
  #19 = Utf8               this
  #20 = Utf8               Lcom/toss/vertx/Test;
  #21 = Utf8               getName
  #22 = Utf8               ()Ljava/lang/String;
  #23 = String             #24            // Hello World
  #24 = Utf8               Hello World
  #25 = Utf8               SourceFile
  #26 = Utf8               Test.java
{
  protected java.lang.String name;
    descriptor: Ljava/lang/String;
    flags: ACC_PROTECTED

  public com.toss.vertx.Test(java.lang.String);
    descriptor: (Ljava/lang/String;)V
    flags: ACC_PUBLIC
    Code:
      stack=2, locals=2, args_size=2
         0: aload_0
         1: invokespecial #12                 // Method java/lang/Object."<init>":()V
         4: aload_0
         5: aload_1
         6: putfield      #15                 // Field name:Ljava/lang/String;
         9: return
      LineNumberTable:
        line 6: 0
        line 7: 4
        line 8: 9
      LocalVariableTable:
        Start  Length  Slot  Name   Signature
            0      10     0  this   Lcom/toss/vertx/Test;
            0      10     1  name   Ljava/lang/String;

  public java.lang.String getName();
    descriptor: ()Ljava/lang/String;
    flags: ACC_PUBLIC
    Code:
      stack=2, locals=1, args_size=1
         0: aload_0
         1: ldc           #23                 // String Hello World
         3: putfield      #15                 // Field name:Ljava/lang/String;
         6: aload_0
         7: getfield      #15                 // Field name:Ljava/lang/String;
        10: areturn
      LineNumberTable:
        line 11: 0
        line 12: 6
      LocalVariableTable:
        Start  Length  Slot  Name   Signature
            0      11     0  this   Lcom/toss/vertx/Test;
}
SourceFile: "Test.java"
{% endcodeblock %}
猛地一看有些晕但是当你细细的研究这些，就会发现很有趣。其结构遵循了之前所讲的结构，下面我将会一一介绍。
## 常量池
最重要的莫过于常量池这个部分，常量池顾名思义，保存不会变动的数据。它可以有效的帮助Jvm在运行时定位相关的数据及结构信息，从而脱离对其它类、接口、实例或是数组的依赖。下面梳理一下常量池通常包含的数据：
- Utf8：表示可被引用的值
- Class：通常会引用一个Utf8来表示一个类。例：#1就是一个Class类型但是借助了#2来表示出其具体类型。
- NameAndType：组合类型，来表示一个未定义类的字段或方法。如：#16就仅仅表示一个String类型的name。
- Fieldref：由Class.NameAndType组成一个特定类型的字段。如：#15就标明了一个Test类下String类型的name字段。
- Methodref：由Class.NameAndType组成特定类型的方法。例：#12
- 方法中的字符串，静态的integer，float以及双字节长度的double long也会被纳入常量池中。

这可以看到一个类的核心信息都可在常量池中找到，像字段，方法，继承的类，实现的接口。这些只是常量池中比较常见的几种类型，更为详细的类型可以查阅官网文档，这里就不再一一叙述。
## 字段信息（field_info）方法信息（method_info）
每个字段都是由field_info结构描述，每个方法（包括每个实例初始化方法类或接口初始化方法）都由method_info结构描述。
{% codeblock %}
field_info {
    u2             access_flags;
    u2             name_index;
    u2             descriptor_index;
    u2             attributes_count;
    attribute_info attributes[attributes_count];
}
method_info {
    u2             access_flags;
    u2             name_index;
    u2             descriptor_index;
    u2             attributes_count;
    attribute_info attributes[attributes_count];
}
{% endcodeblock %}
可以看到两者的结构都是十分类似的，均由访问符、描述和附加属性表组成。访问符标识了字段或方法的访问类型，详细类型可前往官网查看。描述则是引用自常量池的数据。可以看到attribute_info在class，feild，method的结构中都有出现，因此在下一个小结中将会介绍attribute_info。
## 属性信息（attribute_info）
属性信息存在于ClassFile, field_info, method_info以及Code_attribute中，具体分类可以查阅官网的{% link 表格列表 https://docs.oracle.com/javase/specs/jvms/se8/html/jvms-4.html#jvms-4.7-300 %}，由于数量众多，此处仅选取几个常见并且比较重要的来做下介绍。
- ConstantValue：存在于field_info结构中，当字段是静态变量时会在类或接口初始化之前将值赋给静态变量。 
- Code：method_info结构中的属性，出现在方法或是构造方法中，只会存在一个Code但是当方法是native或是abstract修饰时将不会出现。其具有方法执行时的具体指令，操作数栈深度，局部变量个数（包括了形参数量）和附加的属性信息，如LineNumberTable、LocalVariableTable、exception表。
- LineNumberTable：存在于Code属性信息，展示了java源码文件的行号和code指令索引值的对应关系。例如其中的line 6: 0就意味着code指令索引0对应源码第6行。
- LocalVariableTable：存在于Code属性信息，在上篇文章中已经介绍过，是局部变量的一个表，具体记录了指令中的局部变量后缀。
- Exceptions：存在于method_info结构中用于表示可能出现的异常、异常的捕获范围及处理指令。一个method_info只会拥有一个这样的结构。
- StackMapTable：存在于Code的属性信息，Code中最多出现一次，Jvm运行过程中的类型检查使用到的信息。
# 写在最后
从javap指令上看节码信息大概就是这些，但是由于精力有限只能介绍到这里，第四章内容还有部分内容是讲类型检查，有想要深入了解的可以去官网学习。
