---
title: Java参数传递探究
date: 2019-03-24 09:56:30
tags:
- Java
- Jvm
---
今年以来学习劲头没以前那般积极了，这可不是什么好兆头。想了想主要是没遇到啥问题需要记录，于是上开源中国的问答区看看，还真就找到了些问题值得我学习思考的，于是记录一下，本篇文章将具体解答开源中国上[一个关于类型和传参的问题](https://www.oschina.net/question/3622405_2304212)。
<!-- more -->

# 问题引出

```java
public class Question {
    public static void main(String[] args) {
        Integer i = 0;
        add(i);
    }

    public static void add(Integer i) {
        i += 1;
    }
}
```

开源中国上的问题主要是想知道main中的i最后输出是多少，是不是加1之后的值？

# 问题详解

诚如我在答案中提到的那样：Java是一个奇怪的语言，编写的源码要编译成字节码文件，再由Jvm执行。所以我们需要搞清楚究竟发生了什么，是需要查看字节码文件。

## 查看字节码

通过Jdk字节码查看命令javap，在控制台输入javap -c Question.class可以得到如下主要的内容

```bash
  public static void main(java.lang.String[]);
    Code:
       0: iconst_0
       1: invokestatic  #2                  // Method java/lang/Integer.valueOf:(I)Ljava/lang/Integer;
       4: astore_1
       5: aload_1
       6: invokestatic  #3                  // Method add:(Ljava/lang/Integer;)V
       9: return
      LocalVariableTable:
        Start  Length  Slot  Name   Signature
            0      10     0  args   [Ljava/lang/String;
            5       5     1     i   Ljava/lang/Integer;

  public static void add(java.lang.Integer);
    Code:
       0: aload_0
       1: invokevirtual #4                  // Method java/lang/Integer.intValue:()I
       4: iconst_1
       5: iadd
       6: invokestatic  #2                  // Method java/lang/Integer.valueOf:(I)Ljava/lang/Integer;
       9: astore_0
      10: return
      LocalVariableTable:
        Start  Length  Slot  Name   Signature
            0      11     0     i   Ljava/lang/Integer;
```

## 分析字节码

这里涉及字节码结构和jvm指令的知识，不复杂只需要耐心分析。这里只看方法区域的两部分即可：

- Code：jvm执行的代码
- LocalVariableTable:方法的局部变量表

先从main方法Code一行一行

- 0加载原始类型常量0
- 1调用Integer.valueOf方法包装为Integer
- 4存储Integer至局部变量表Slot为1的i中，自此完成对i的初始化
- 5加载局部变量i
- 6调用add方法

接着看看add方法中发生了什么

- 0加载add中局部变量表Slot为0的i
- 1调用方法Integer.intValue转为原始类型
- 4加载原始类型常量1
- 5数值相加
- 6调用Integer.valueOf方法包装为Integer
- 9存储Integer至i中
- 10完成add方法返回

所以在Jvm眼中我们的代码其实是如下样子

```java
public class Question {
    public static void main(String[] args) {
        Integer i = Integer.valueOf(0);
        add(i);
    }

    public static void add(Integer i) {
        i = Integer.valueOf(i.intValue() + 1);
    }
}
```

如果不相信的话可以将上述代码的字节码文件反编译下，可以得到之前一样的结果。

## 问题解答

这时main中变量i仍然指向堆中值为0的Integer的对象，而add中的i却已经只向值为1的Integer对象。有的人会认为main中的i不是和add中的i是一样，这就涉及到Java方法执行的参数的处理，一言以蔽之：Java方法调用是局部变量之间赋值转移，参数也只是个局部变量。可以看到main中的参数args同样是出现在局部变量表中Slot为0变量，在调add方法前的步骤5加载局部变量i，就是为add中变量i做赋值准备，那么例子就可以理解为如下内容

```Java
   public static void main(String[] args) {
        Integer main_i = Integer.valueOf(0);
        Integer add_i = main_i;
        add_i = Integer.valueOf(add_i.intValue() + 1);
    }
```

这样可以清晰的看出main中的i和add中的i的已是完全不同的Integer对象。

# 写在最后

本来是闲来无事所以探究一番，不曾想加深对于Java的理解，以后多看看别人的问题，自己解决之后也可以得到一定的提升。