---
title: Java字段初始化
date: 2019-04-04 21:11:52
tags:
- Java
---
之前在开源中国的问答区有一个问题一直想记录，结果拖拖拉拉的搞到现在才记录。这是关于[Java字段初始化顺序](https://www.oschina.net/question/3087363_2304230)的问题，这个问题很有意思，不注意就会掉入陷阱，下面就开始介绍这个问题。
<!-- more -->

# 问题引出

```java
public class Question {
    static Question question = new Question();// 1
    static {
        x = 2;// 2
    }
    static int x = 1;// 3
    public Question() {
        y = 3;// 4
    }
    {
        y = 2;// 5
    }
    int y = 1;// 6
}
```

上面这个问题中我们观察到有类变量和实例变量，也有代码块static{}和{}。这两种代码块在官方的[Java™教程](https://docs.oracle.com/javase/tutorial/java/javaOO/initial.html)中称为：

- static{} 静态初始化块(Static Initialization Blocks)
- {} 初始化块(initializer blocks)，是初始化实例变量的两种方式之一，本文就称之为实例初始化块

静态初始化块在类加载期运行，实例初始化块在对象创建时运行。下面引出问题，上面这段代码执行的顺序是什么，是由上向下的123456吗？

# 问题分析

一开始这个问题还真把我给难到了，但是想想解决之后肯定会得到成长，于是研究了一番。

## 查看字节码

直接请出我们的好帮手javap，查看编出的字节码就是是什么样子的。

```bash
  public Question();
    descriptor: ()V
    flags: ACC_PUBLIC
    Code:
      stack=2, locals=1, args_size=1
         0: aload_0
         1: invokespecial #1                  // Method java/lang/Object."<init>":()V
         4: aload_0
         5: iconst_2
         6: putfield      #2                  // Field y:I
         9: aload_0
        10: iconst_1
        11: putfield      #2                  // Field y:I
        14: aload_0
        15: iconst_3
        16: putfield      #2                  // Field y:I
        19: return
      LocalVariableTable:
        Start  Length  Slot  Name   Signature
            0      20     0  this   LQuestion;

  static {};
    descriptor: ()V
    flags: ACC_STATIC
    Code:
      stack=2, locals=0, args_size=0
         0: new           #3                  // class Question
         3: dup
         4: invokespecial #4                  // Method "<init>":()V
         7: putstatic     #5                  // Field question:LQuestion;
        10: iconst_2
        11: putstatic     #6                  // Field x:I
        14: iconst_1
        15: putstatic     #6                  // Field x:I
        18: return
```

## 字节码分析

又是字节码分析，so easy。之前提到static{}静态初始化代码类加载期就执行，所以先从static{}开始

- 0：新建Question对象
- 3：复制操作数栈顶值
- 4：调用Question的构造方法
- 7：将Question对象放入类变量question
- 10：加载常量2
- 11：放入类变量x
- 14：加载常量1
- 15：放入类变量x

**注意**：在第4行的时候就已经进入到Question的构造方法中去了，下面看看构造方法是什么样的：

- 0：加载本地变量this
- 1：调用Object的构造方法
- 4：加载本地变量this
- 5：加载常量2
- 6：将this的实例变量y赋值

后面皆是重复的赋值步骤就不再细讲。到这里我们可以知晓答案是：156423。但这是怎么回事？

## 问题详解

从官方的文档中找到的相关信息

- 静态初始化块：详细的初始化程序中的第九步，[按文本顺序执行类的类变量初始值设定项和类的静态初始值设定项，或接口的字段初始值设定项，就好像它们是单个块一样](https://docs.oracle.com/javase/specs/jls/se8/html/jls-12.html#jls-12.4.2)
- 实例初始化块：[Java编译器将初始化程序块复制到每个构造函数中。因此，该方法可用于在多个构造函数之间共享代码块](https://docs.oracle.com/javase/tutorial/java/javaOO/initial.html)

静态初始化块和实例初始化块都不辜负名字里的初始化，分别初始化类变量，实例变量。最为关键一点：**字段初始值设定项，就好像它们是单个块一样**，这意味着什么？意味字段初始值设定其实是两部分：变量声明，相应的赋值块语句。所以最原本的样子应该是：

```java
public class Question {
    static Question question;
    static {
        question = new Question();
    }
    static {
        x = 2;
    }
    static int x;
    static {
        x = 1;
    }
    public Question() {
        y = 3;
    }
    {
        y = 2;
    }
    int y;
    {
        y = 1;
    }
}
```

这样是不是清楚了些，代码块依旧是由上向下执行，实例初始化块在每个构造函数中是优先执行的，所以y=3在y=2y=1之后执行的。再整合一下就是下面这个样子:

```java
public class Question {
    static Question question;
    static {
        question = new Question();
        x = 2;
        x = 1;
    }
    static int x;
    {
        y = 2;
        y = 1;
    }
    public Question() {
        y = 3;
    }
    int y;
}
```

# 写在最后

原本我看到这个问题也是不清楚的，但是经过一番探究最后得到答案，加深了对java的了解同时也提醒了自己，避免以后陷入同样的问题。另外官网中[字段的前向引用](https://docs.oracle.com/javase/specs/jls/se8/html/jls-8.html#jls-8.3.3)介绍了字段间引用关系，非常值得一看。